pyghidra_mcp/__init__.py
pyghidra_mcp/__main__.py
pyghidra_mcp/context.py
pyghidra_mcp/models.py
pyghidra_mcp/py.typed
pyghidra_mcp/server.py
pyghidra_mcp/tools.py
pyghidra_mcp-0.1.13.dist-info/METADATA
pyghidra_mcp-0.1.13.dist-info/WHEEL
pyghidra_mcp-0.1.13.dist-info/entry_points.txt
pyghidra_mcp-0.1.13.dist-info/licenses/LICENSE
pyghidra_mcp-0.1.13.dist-info/RECORD
