Metadata-Version: 2.4
Name: pyghidra-mcp
Version: 0.1.13
Summary: Python Command-Line Ghidra MCP
Author-email: clearbluejar <3752074+clearbluejar@users.noreply.github.com>, notoriousrip <3935212+unimpossible@users.noreply.github.com>
License-File: LICENSE
Keywords: dynamic-analysis,ghidra,mcp,pyghidra,reverse-engineering,security,static-analysis
Classifier: Development Status :: 4 - Beta
Classifier: Intended Audience :: Developers
Classifier: Programming Language :: Python :: 3
Classifier: Programming Language :: Python :: 3.10
Classifier: Programming Language :: Python :: 3.11
Classifier: Programming Language :: Python :: 3.12
Classifier: Programming Language :: Python :: 3.13
Classifier: Topic :: Security
Requires-Python: >=3.10
Requires-Dist: chromadb>=1.3.5
Requires-Dist: click-option-group>=0.5.9
Requires-Dist: click>=8.2.1
Requires-Dist: ghidrecomp>=0.5.8
Requires-Dist: mcp[cli]>=1.9.4
Requires-Dist: pyghidra>=2.2.1
Provides-Extra: dev
Requires-Dist: aiohttp; extra == 'dev'
Requires-Dist: ghidra-stubs>=11.3.2; extra == 'dev'
Requires-Dist: mcp[cli]>=1.11.0; extra == 'dev'
Requires-Dist: pre-commit>=3.0.0; extra == 'dev'
Requires-Dist: pyright>=1.1.0; extra == 'dev'
Requires-Dist: pytest-asyncio>=0.23.0; extra == 'dev'
Requires-Dist: pytest-cov>=6.2.1; extra == 'dev'
Requires-Dist: pytest>=8.4.1; extra == 'dev'
Requires-Dist: ruff>=0.11.4; extra == 'dev'
Requires-Dist: tomli-w>=1.0.0; extra == 'dev'
Requires-Dist: tomli>=2.0.1; extra == 'dev'
Requires-Dist: uv>=0.8.11; extra == 'dev'
